<annotation>
	<folder></folder>
	<filename>1-3-6-1-4-1-14519-5-2-1-6279-6001-124154461048929153767743874565_41_86_png.rf.e69e1761e21d9726426cc6fbbeadda81.jpg</filename>
	<path>1-3-6-1-4-1-14519-5-2-1-6279-6001-124154461048929153767743874565_41_86_png.rf.e69e1761e21d9726426cc6fbbeadda81.jpg</path>
	<source>
		<database>roboflow.com</database>
	</source>
	<size>
		<width>512</width>
		<height>512</height>
		<depth>3</depth>
	</size>
	<segmented>0</segmented>
	<object>
		<name>nodule</name>
		<pose>Unspecified</pose>
		<truncated>0</truncated>
		<difficult>0</difficult>
		<occluded>0</occluded>
		<bndbox>
			<xmin>444</xmin>
			<xmax>459</xmax>
			<ymin>305</ymin>
			<ymax>320</ymax>
		</bndbox>
	</object>
</annotation>
